head_to_py/__init__.py
head_to_py/head_to_py.py
head_to_py-0.0.2.dist-info/METADATA
head_to_py-0.0.2.dist-info/WHEEL
head_to_py-0.0.2.dist-info/top_level.txt
head_to_py-0.0.2.dist-info/RECORD
